{
  "type": "object",
  "$schema": "http://json-schema.org/draft-04/schema",
  "title": "Ideal Stock Amount",
  "description": "A single isa object",
  "properties": {
    "id": {
      "type": "string",
      "title": "id"
    },
    "facility": {
      "type": "object",
      "$ref": "basicFacilityDto.json"
    },
    "program": {
      "type": "object",
      "$ref": "program.json"
    },
    "orderable": {
      "type": "object",
      "$ref": "orderable.json"
    },
    "processingPeriod": {
      "type": "object",
      "$ref": "processingPeriod.json"
    },
    "amount": {
      "type": "sting",
      "title": "amount"
    },
  },
  "required": [
    "facility",
    "program",
    "orderable",
    "processingPeriod",
    "amount"
  ]
}
